evlos_tools/deploy/export.py
evlos_tools/deploy/tensorrt_async.py
evlos_tools/exposure_fusion/README.md
evlos_tools/exposure_fusion/main.py
evlos_tools/exposure_fusion/models.py
evlos_tools/exposure_fusion/utils.py
evlos_tools/exposure_fusion/configs/exposure_fusion.yaml
evlos_tools/exposure_fusion/resources/engines/.gitkeep
evlos_tools/exposure_fusion/resources/onnx/.gitkeep
evlos_tools/template_matcher/template_matching.py
evlos_tools/template_matcher/utils.py
evlos_tools/template_matcher/feature_extractor/aliked.py
evlos_tools/template_matcher/feature_extractor/disk.py
evlos_tools/template_matcher/feature_extractor/sift.py
evlos_tools/template_matcher/lightglue/lightglue.py
evlos_tools/template_matcher/lightglue/utils.py
evlos_tools/template_matcher/lightglue/viz2d.py
evlos_tools/template_matcher/resources/engines/.gitkeep
evlos_tools-0.1.0.dist-info/METADATA
evlos_tools-0.1.0.dist-info/WHEEL
evlos_tools-0.1.0.dist-info/RECORD
